django_admin_ai_search/__init__.py
django_admin_ai_search/apps.py
django_admin_ai_search/prompt.py
django_admin_ai_search/protocols.py
django_admin_ai_search/schema.py
django_admin_ai_search/services.py
django_admin_ai_search/urls.py
django_admin_ai_search/views.py
django_admin_ai_search/templates/admin/index.html
django_admin_ai_search-0.1.1.dist-info/METADATA
django_admin_ai_search-0.1.1.dist-info/WHEEL
django_admin_ai_search-0.1.1.dist-info/licenses/LICENSE
django_admin_ai_search-0.1.1.dist-info/RECORD
