Metadata-Version: 2.4
Name: django-admin-ai-search
Version: 0.1.1
Summary: AI-powered natural language search for Django Admin
Project-URL: Homepage, https://github.com/quanhea/django-admin-ai-search
Project-URL: Documentation, https://github.com/quanhea/django-admin-ai-search#readme
Project-URL: Repository, https://github.com/quanhea/django-admin-ai-search
Project-URL: Issues, https://github.com/quanhea/django-admin-ai-search/issues
Author-email: Anh Tran <anh.q.tran@eastagile.com>
License-Expression: MIT
License-File: LICENSE
Keywords: admin,ai,django,llm,natural-language,search
Classifier: Development Status :: 3 - Alpha
Classifier: Environment :: Web Environment
Classifier: Framework :: Django
Classifier: Framework :: Django :: 4.2
Classifier: Framework :: Django :: 5.0
Classifier: Intended Audience :: Developers
Classifier: License :: OSI Approved :: MIT License
Classifier: Operating System :: OS Independent
Classifier: Programming Language :: Python :: 3
Classifier: Programming Language :: Python :: 3.10
Classifier: Programming Language :: Python :: 3.11
Classifier: Programming Language :: Python :: 3.12
Classifier: Topic :: Internet :: WWW/HTTP :: Dynamic Content
Requires-Python: >=3.10
Requires-Dist: django>=4.2
